goodlogging/__init__.py
goodlogging/goodlogging.py
goodlogging-1.0.1.dist-info/DESCRIPTION.rst
goodlogging-1.0.1.dist-info/METADATA
goodlogging-1.0.1.dist-info/RECORD
goodlogging-1.0.1.dist-info/WHEEL
goodlogging-1.0.1.dist-info/metadata.json
goodlogging-1.0.1.dist-info/top_level.txt
