Metadata-Version: 1.0
Name: goodlogging
Version: 1.0.1
Summary: Logging module for command line utilities
Home-page: http://github.com/davgeo/goodlogging
Author: David George
Author-email: dcg.git@gmail.com
License: MIT
Platform: UNKNOWN
